[
  {
    "page_id": "3af2bb14061e4f83ba4a7789bcc6dd55",
    "title": "$1000 or $4000 off a Used Electric Vehicle"
  },
  {
    "page_id": "f29e5aef57dc41a0b827052e1f6c7b3a",
    "title": "$15 Bonus Calfresh at the Nevada City Farmers Market"
  },
  {
    "page_id": "206fc8296c7f404a82f52335c4d380c5",
    "title": "$15 HotSpot. Mobile Beacon for Nonprofits"
  },
  {
    "page_id": "57d151132c05418ebbdc55f77f3082cd",
    "title": "$2,000 Scholarship \\"
  },
  {
    "page_id": "0c05f6eb5eec4a9cbcfc676fceec544c",
    "title": "$200 off per ton mini split"
  },
  {
    "page_id": "fb59fed69cca4bf18eb2565a4dd1f314",
    "title": "$325 Bonus Checking Accounts \u2014 Wells Fargo"
  },
  {
    "page_id": "4cf17eb54625410ea3a50cd2da20349c",
    "title": "$75 off Smart thermostats \\"
  },
  {
    "page_id": "158a4ee6952081b0a9c5fbf73702650c",
    "title": "$8000 mini split TECH Public Reporting HEEHRA Rebates"
  },
  {
    "page_id": "196383850c5649f59c769051bf8ab5bd",
    "title": "$900 off Heat pump water heaters \\"
  },
  {
    "page_id": "309a4ee695208102aa7bc6b4384eb692",
    "title": "1yr student Google AI One Plans free"
  },
  {
    "page_id": "3278ca2c34474ec28e8662efdb38f7f4",
    "title": "2 free mini splits TECH Clean California"
  },
  {
    "page_id": "1ba3ab47615540bf86db2465418ffe9b",
    "title": "2x Free Whole House Batteries - SGIP"
  },
  {
    "page_id": "d810ed0b7f064c6fa88fd280dabd4b94",
    "title": "30% off Federal Tax Credits Pre-owned Plug-in Electric"
  },
  {
    "page_id": "9e70039e90a5475c9bc457f25b410b11",
    "title": "30% Off Used EV Discount up to $4000 \\"
  },
  {
    "page_id": "daaba0248aa34829b49ec3c22f50c517",
    "title": "40% off PG&E CARE and FERA enrollment"
  },
  {
    "page_id": "9fbddb6908194739809eca3d75d29028",
    "title": "AARP Foundation Free Tax-Aide Service"
  },
  {
    "page_id": "1fba4ee69520810cbd6beb3e8805e38d",
    "title": "All Residential Services - Northern Rural Energy Network"
  },
  {
    "page_id": "12aa4ee695208171bd80ffc7e321fb34",
    "title": "Auburn \\"
  },
  {
    "page_id": "d4cf4feb49174c40a57784d54ecb522b",
    "title": "Auto Body Inspection Program - Bureau of Automotive Repair"
  },
  {
    "page_id": "0d7dc4633dba4c5a8d2aec346463961b",
    "title": "AWS IMAGINE Grant Program - Nonprofit"
  },
  {
    "page_id": "1a2a4ee69520814da015e428b3ccb803",
    "title": "Battery storage for homeowners"
  },
  {
    "page_id": "eb26ca5fdd65491cac653dd91719fc64",
    "title": "Borrow a Hotspot \\"
  },
  {
    "page_id": "892ef11a38ef408ba1afe38af3ac3eae",
    "title": "Bright Futures for Youth \\"
  },
  {
    "page_id": "1baa4ee695208123923dfbf553740f02",
    "title": "CAEATFA GoGreen Home Energy Financing"
  },
  {
    "page_id": "1fc79846163c4ab18bf4a5ca3e35f556",
    "title": "Cal-works at BenefitsCal"
  },
  {
    "page_id": "17ba4ee6952081abaa29ef9f06c24f72",
    "title": "California Advanced Services Fund (CASF) Adoption Account"
  },
  {
    "page_id": "a5a9f895c1b04fbaa2c922a896fa3a0a",
    "title": "California Fruit & Vegetable EBT Pilot Project"
  },
  {
    "page_id": "14ca4ee6952081579b9cc16cf4f92234",
    "title": "California State Library Parks Pass"
  },
  {
    "page_id": "3dd7f4a74ce14867bbee93529e229986",
    "title": "California Volunteers"
  },
  {
    "page_id": "498130c4e80c4bbaa07f5df09baf7818",
    "title": "Camunda for Nonprofits"
  }
]