[
  {
    "page_id": "0fbe77bb73674a1a8cbd1fd15404775e",
    "title": "Cash Access - California EBT Surcharge-Free ATMs"
  },
  {
    "page_id": "fedbeb2159d14b2c9448341c2db4dc0b",
    "title": "Cash App Taxes - Free Tax Filing"
  },
  {
    "page_id": "70e6fe9f76a642f5b0969c7e8945649c",
    "title": "Cash Assistance for Individuals \\"
  },
  {
    "page_id": "bf74159fe9e9413db683d7a1eb00f935",
    "title": "CDFA - Grant Programs"
  },
  {
    "page_id": "11c670fa432c401798c7595caeaed74c",
    "title": "CDFA - Resilient Food Systems Infrastructure Program"
  },
  {
    "page_id": "171a4ee6952081e0a752ed7386592ecc",
    "title": "CDFA - Senior Farmers' Market Nutrition Program"
  },
  {
    "page_id": "16ea4ee6952081f98fc2f01ef7207971",
    "title": "Check Your Eligibility \\"
  },
  {
    "page_id": "2d1dc6185a4a472cad58a6ee0c3a3216",
    "title": "Consumer Assistance Program Smog Repair Assistance"
  },
  {
    "page_id": "e7fe822a941b45848cbfa20f4e5be78f",
    "title": "Crisis Care Services and Support \\"
  },
  {
    "page_id": "309a4ee69520815585eed47eb0918146",
    "title": "Cursor \u00b7 Students free 1 year"
  },
  {
    "page_id": "dbfbc5eb89bd4dba9affceafc6103491",
    "title": "Ebike School presents Ebikes For Good"
  },
  {
    "page_id": "9b89ea58280448bea86ffcb706a7fe82",
    "title": "Electric Vehicles rates for residential PGE customers"
  },
  {
    "page_id": "e7c02901686d4037bdfd6c36242fb803",
    "title": "Energy Savings Assistance Program pge.com"
  },
  {
    "page_id": "59d2139c5a8743f3b35bab4cbc13a495",
    "title": "Energy Smart Homes - Whole House Rebate"
  },
  {
    "page_id": "25ca4ee6952081df95ffc6199b49813d",
    "title": "Enhanced Care Management QIP"
  },
  {
    "page_id": "3da77becf8bc454d9213419417ea8de8",
    "title": "Environmental Quality Incentives Program \\"
  },
  {
    "page_id": "c90563df9ee24f5b9aa69e2296e4fc71",
    "title": "FARMER GRANTS \\"
  },
  {
    "page_id": "891cae84b4c240db81ce13b474c08736",
    "title": "Financial Aid Programs - California Student Aid Commission"
  },
  {
    "page_id": "170a4ee6952081a8a424e740d6781a1c",
    "title": "Find a Dentist \\"
  },
  {
    "page_id": "49ffcaffe9f14c7d81a7ba029313a461",
    "title": "FoodFinder maps food resources"
  },
  {
    "page_id": "68bafd766c274ea6a5704f8f4b39ebb0",
    "title": "Form a Nonprofit in California - a Complete Guide"
  },
  {
    "page_id": "ec47d6bb0397472586a3e785c0a268b3",
    "title": "Free $500 Generator or Battery Program - PGE"
  },
  {
    "page_id": "ad3f47de18ae469c8be34c07c40d3e94",
    "title": "Free Adobe Express for Nonprofits"
  },
  {
    "page_id": "300a4ee6952080a5ade8f57aa96b7d23",
    "title": "Free AI Coding Assistant: Complete Guide"
  },
  {
    "page_id": "271a5b67e208486ea7603864b4b5df84",
    "title": "FREE Backup Power Transfer Meter Program"
  },
  {
    "page_id": "dc610873902b4f8ab406082ad3908011",
    "title": "Free Cannabis Compassion Program \u2022 Elevation 2477'"
  },
  {
    "page_id": "b3cba50defb34873a3a05b287cc2df49",
    "title": "Free Canva Nonprofit"
  },
  {
    "page_id": "0ea2a7311a7f4bd6b9a23195f74b0b05",
    "title": "Free College Saving Accounts - CalKIDS"
  },
  {
    "page_id": "0bd99e4e61c840ddaae8fcb4a7558cf0",
    "title": "Free Electric Vehicle Charger (Level 2) - Empower EV"
  },
  {
    "page_id": "df7369e29a364fc2858863ba8351fdee",
    "title": "Free Fiber - California Line Extension Program"
  }
]